[ {"":[16,16],"pattern":"(...)","fields":["0","1"],"rule":"union:input"},
  {"":[0,0],"pattern":"<...>","fields":["x","y"],"rule":"union:output"},
  {"":[16,16],"pattern":"(...)","fields":["0","1"],"rule":"union:input"},
  {"":[0,0],"pattern":"<...>","fields":["x","y"],"rule":"union:output"},
  {"":[16,16],"pattern":"(...)","fields":["0","1"],"rule":"union:input"},
  {"":[10,10],"pattern":"(...)","fields":["x","y","z"],"rule":"union:input."},
  {"":[10,10],"pattern":"(...)","fields":["x","y","z"],"rule":"union:input."},
  {"":[15,15],"pattern":"(...)","fields":[],"rule":"comp:chain"},
  {"":[15,15],"pattern":"(...)","fields":[],"rule":"comp:chain"},
  {"":[0,0],"pattern":"<...>","fields":["x","y"],"rule":"union:output"},
  {"":[15,15],"pattern":"(...)","fields":[],"rule":"comp:chain"},
  {"":[4,4],"pattern":"type","type":"KL"},
  {"":[16,16],"pattern":"(...)","fields":["0","1"],"rule":"union:input"},
  {"":[0,0],"pattern":"<...>","fields":["x","y"],"rule":"union:output"},
  {"":[16,16],"pattern":"(...)","fields":["0","1"],"rule":"union:input"},
  {"":[1,1],"pattern":"{}","fields":["0","1"],"rule":"comp:chain"},
  {"":[16,16],"pattern":"(...)","fields":["0","1"],"rule":"union:input"},
  {"":[3,3],"pattern":"(...)","fields":[]},
  {"":[16,16],"pattern":"(...)","fields":["0","1"],"rule":"union:input"},
  {"":[23,23],"pattern":"[]","fields":["vector-member"],"rule":"comp:chain"},
  {"":[16,16],"pattern":"(...)","fields":["0","1"],"rule":"union:input"},
  {"":[14,14],"pattern":"(...)","fields":[],"rule":"vector:output"},
  {"":[16,16],"pattern":"(...)","fields":["0","1"],"rule":"union:input"},
  {"":[10,10],"pattern":"(...)","fields":["x","y","z"],"rule":"union:input."},
  {"":[10,10],"pattern":"(...)","fields":["x","y","z"],"rule":"union:input."},
  {"":[13,13],"pattern":"(...)","fields":["0"],"rule":"comp:chain"},
  {"":[13,13],"pattern":"(...)","fields":["0"],"rule":"comp:chain"},
  {"":[14,14],"pattern":"(...)","fields":[],"rule":"vector:output"},
  {"":[23,23],"pattern":"[]","fields":["vector-member"],"rule":"comp:chain"},
  {"":[3,3],"pattern":"(...)","fields":[]},
  {"":[16,16],"pattern":"(...)","fields":["0","1"],"rule":"union:input"},
  {"":[2,2],"pattern":"(...)","fields":[]},
  {"":[16,16],"pattern":"(...)","fields":["0","1"],"rule":"union:input"},
  {"":[22,22],"pattern":"[]","fields":["vector-member"],"rule":"comp:chain"},
  {"":[16,16],"pattern":"(...)","fields":["0","1"],"rule":"union:input"},
  {"":[9,9],"pattern":"(...)","fields":[],"rule":"vector:output"},
  {"":[16,16],"pattern":"(...)","fields":["0","1"],"rule":"union:input"},
  {"":[5,5],"pattern":"(...)","fields":["y","z"],"rule":"union:input."},
  {"":[5,5],"pattern":"(...)","fields":["y","z"],"rule":"union:input."},
  {"":[8,8],"pattern":"(...)","fields":["1"],"rule":"comp:chain"},
  {"":[8,8],"pattern":"(...)","fields":["1"],"rule":"comp:chain"},
  {"":[9,9],"pattern":"(...)","fields":[],"rule":"vector:output"},
  {"":[22,22],"pattern":"[]","fields":["vector-member"],"rule":"comp:chain"},
  {"":[2,2],"pattern":"(...)","fields":[]},
  {"":[1,1],"pattern":"{}","fields":["0","1"],"rule":"comp:chain"},
  {"":[0,0],"pattern":"<...>","fields":["x","y"],"rule":"union:output"},
  {"":[1,1],"pattern":"{}","fields":["0","1"],"rule":"comp:chain"},
  {"":[1,1],"pattern":"{}","fields":["0","1"],"rule":"comp:chain"},
  {"":[16,16],"pattern":"(...)","fields":["0","1"],"rule":"union:input"},
  {"":[0,0],"pattern":"<...>","fields":["x","y"],"rule":"union:output"},
  {"":[16,16],"pattern":"(...)","fields":["0","1"],"rule":"union:input"},
  {"":[17,17],"pattern":"{}","fields":["0","1"],"rule":"comp:chain"},
  {"":[16,16],"pattern":"(...)","fields":["0","1"],"rule":"union:input"},
  {"":[19,19],"pattern":"(...)","fields":[]},
  {"":[16,16],"pattern":"(...)","fields":["0","1"],"rule":"union:input"},
  {"":[21,21],"pattern":"[]","fields":["vector-member"],"rule":"comp:chain"},
  {"":[16,16],"pattern":"(...)","fields":["0","1"],"rule":"union:input"},
  {"":[12,12],"pattern":"(...)","fields":[],"rule":"vector:output"},
  {"":[16,16],"pattern":"(...)","fields":["0","1"],"rule":"union:input"},
  {"":[10,10],"pattern":"(...)","fields":["x","y","z"],"rule":"union:input."},
  {"":[10,10],"pattern":"(...)","fields":["x","y","z"],"rule":"union:input."},
  {"":[11,11],"pattern":"(...)","fields":["0"],"rule":"comp:chain"},
  {"":[11,11],"pattern":"(...)","fields":["0"],"rule":"comp:chain"},
  {"":[12,12],"pattern":"(...)","fields":[],"rule":"vector:output"},
  {"":[21,21],"pattern":"[]","fields":["vector-member"],"rule":"comp:chain"},
  {"":[19,19],"pattern":"(...)","fields":[]},
  {"":[16,16],"pattern":"(...)","fields":["0","1"],"rule":"union:input"},
  {"":[18,18],"pattern":"(...)","fields":[]},
  {"":[16,16],"pattern":"(...)","fields":["0","1"],"rule":"union:input"},
  {"":[20,20],"pattern":"[]","fields":["vector-member"],"rule":"comp:chain"},
  {"":[16,16],"pattern":"(...)","fields":["0","1"],"rule":"union:input"},
  {"":[7,7],"pattern":"(...)","fields":[],"rule":"vector:output"},
  {"":[16,16],"pattern":"(...)","fields":["0","1"],"rule":"union:input"},
  {"":[5,5],"pattern":"(...)","fields":["y","z"],"rule":"union:input."},
  {"":[5,5],"pattern":"(...)","fields":["y","z"],"rule":"union:input."},
  {"":[6,6],"pattern":"(...)","fields":["1"],"rule":"comp:chain"},
  {"":[6,6],"pattern":"(...)","fields":["1"],"rule":"comp:chain"},
  {"":[7,7],"pattern":"(...)","fields":[],"rule":"vector:output"},
  {"":[20,20],"pattern":"[]","fields":["vector-member"],"rule":"comp:chain"},
  {"":[18,18],"pattern":"(...)","fields":[]},
  {"":[17,17],"pattern":"{}","fields":["0","1"],"rule":"comp:chain"},
  {"":[0,0],"pattern":"<...>","fields":["x","y"],"rule":"union:output"}
]